rucio_consistency/__init__.py
rucio_consistency/cmplib.py
rucio_consistency/config-with-rucio-backend.py
rucio_consistency/config.py
rucio_consistency/part.py
rucio_consistency/py3.py
rucio_consistency/stats.py
rucio_consistency/trace.py
rucio_consistency/version.py
rucio_consistency/scripts/cmp2.py
rucio_consistency/scripts/cmp3.py
rucio_consistency/scripts/cmp5.py
rucio_consistency/scripts/db_dump.py
rucio_consistency/scripts/partition.py
rucio_consistency/scripts/update_stats.py
rucio_consistency/xrootd/__init__.py
rucio_consistency/xrootd/xrootd_client.py
rucio_consistency/xrootd/xrootd_scanner.py
rucio_consistency-1.7.5.dist-info/LICENSE
rucio_consistency-1.7.5.dist-info/METADATA
rucio_consistency-1.7.5.dist-info/WHEEL
rucio_consistency-1.7.5.dist-info/entry_points.txt
rucio_consistency-1.7.5.dist-info/top_level.txt
rucio_consistency-1.7.5.dist-info/RECORD
