Metadata-Version: 2.1
Name: rucio-consistency
Version: 1.7.5
Summary: Common modules and scripts for Rucio consistency enforcement
Home-page: https://github.com/rucio/consistency-enforcement
Author: Igor Mandrichenko
Author-email: ivm@fnal.gov
License: BSD 3-clause
License-File: LICENSE
Requires-Dist: sqlalchemy
Requires-Dist: pythreader
